magicwandmondub/__init__.py
magicwandmondub/audio_recorder.py
magicwandmondub/caption_window_controller.py
magicwandmondub/config.py
magicwandmondub/dubber_ui.py
magicwandmondub/helper.py
magicwandmondub/speech_streamer.py
magicwandmondub-0.1.0.dist-info/METADATA
magicwandmondub-0.1.0.dist-info/WHEEL
magicwandmondub-0.1.0.dist-info/RECORD
